mcp_tourism/__init__.py
mcp_tourism/api_client.py
mcp_tourism/server.py
iflow_mcp_mcp_korea_tourism_api-0.1.2.dist-info/METADATA
iflow_mcp_mcp_korea_tourism_api-0.1.2.dist-info/WHEEL
iflow_mcp_mcp_korea_tourism_api-0.1.2.dist-info/entry_points.txt
iflow_mcp_mcp_korea_tourism_api-0.1.2.dist-info/licenses/LICENSE
iflow_mcp_mcp_korea_tourism_api-0.1.2.dist-info/RECORD
