Metadata-Version: 2.4
Name: iflow-mcp_mcp-korea-tourism-api
Version: 0.1.2
Summary: MCP Server for Korea Tourism API
Project-URL: Repository, https://github.com/harimkang/mcp-korea-tourism-api
Author-email: Harim Kang <harimkang4422@gmail.com>
License-Expression: MIT
License-File: LICENSE
Classifier: Development Status :: 4 - Beta
Classifier: Intended Audience :: Developers
Classifier: Operating System :: OS Independent
Classifier: Programming Language :: Python :: 3
Classifier: Programming Language :: Python :: 3.10
Classifier: Programming Language :: Python :: 3.11
Classifier: Programming Language :: Python :: 3.12
Classifier: Topic :: Software Development :: Libraries :: Application Frameworks
Requires-Python: >=3.12
Requires-Dist: cachetools>=5.5.2
Requires-Dist: fastmcp>=2.13.0
Requires-Dist: httpx>=0.28.1
Requires-Dist: ratelimit>=2.2.1
Requires-Dist: tenacity>=9.1.2
